.hgignore
CHANGES.txt
LICENSE.txt
MANIFEST.in
README.txt
bootstrap.py
buildout.cfg
setup.py
js/__init__.py
js.jquery_tinyscrollbar.egg-info/PKG-INFO
js.jquery_tinyscrollbar.egg-info/SOURCES.txt
js.jquery_tinyscrollbar.egg-info/dependency_links.txt
js.jquery_tinyscrollbar.egg-info/entry_points.txt
js.jquery_tinyscrollbar.egg-info/namespace_packages.txt
js.jquery_tinyscrollbar.egg-info/not-zip-safe
js.jquery_tinyscrollbar.egg-info/requires.txt
js.jquery_tinyscrollbar.egg-info/top_level.txt
js/jquery_tinyscrollbar/__init__.py
js/jquery_tinyscrollbar/test_jquery_tinyscrollbar.txt
js/jquery_tinyscrollbar/resources/README.txt
js/jquery_tinyscrollbar/resources/jquery.tinyscrollbar.js
js/jquery_tinyscrollbar/resources/jquery.tinyscrollbar.min.js