Metadata-Version: 1.0
Name: js.jquery-tinyscrollbar
Version: 1.67
Summary: Fanstatic packaging of jQuery Tiny Scrollbar
Home-page: UNKNOWN
Author: gocept Developers
Author-email: mail@gocept.com
License: BSD
Platform: UNKNOWN
